muster/__init__.py
muster/member.py
muster/servant.py
muster/version.py
muster/utils/__init__.py
muster/utils/compat.py
muster-0.0.1.dist-info/DESCRIPTION.rst
muster-0.0.1.dist-info/LICENSE.txt
muster-0.0.1.dist-info/METADATA
muster-0.0.1.dist-info/RECORD
muster-0.0.1.dist-info/WHEEL
muster-0.0.1.dist-info/metadata.json
muster-0.0.1.dist-info/top_level.txt
