Metadata-Version: 2.0
Name: muster
Version: 0.0.1
Summary: a responsive classes framework
Home-page: https://github.com/rmorshea/muster
Author: Ryan Morshead
Author-email: ryan.morshead@gmail.com
License: MIT
Keywords: attrs,traits,traitlets,descriptors,validation,observe,callbacks
Platform: Linux
Platform: Mac OS X
Platform: Windows
Classifier: Intended Audience :: Developers
Classifier: Programming Language :: Python :: 2.7
Classifier: Programming Language :: Python :: 3.6
